<?xml version="1.0" encoding="UTF-8"?>
<persistence version="2.1" xmlns="http://xmlns.jcp.org/xml/ns/persistence" xmlns:xsi="http://www.w3.org/2001/XMLSchema-instance" xsi:schemaLocation="http://xmlns.jcp.org/xml/ns/persistence http://xmlns.jcp.org/xml/ns/persistence/persistence_2_1.xsd">
	<persistence-unit name="batch_smartoffice">
		<class>com.farmers.batch.kyn.Districtmonthly</class>
		<class>com.farmers.batch.kyn.DistrictmonthlyPK</class>
		<class>com.farmers.batch.kyn.Statemonthly</class>
		<class>com.farmers.batch.kyn.StatemonthlyPK</class>
		<class>com.farmers.batch.kyn.Agentmonthly</class>
		<class>com.farmers.batch.kyn.AgentmonthlyPK</class>
		<class>com.farmers.batch.kyn.Agentaction</class>
		<class>com.farmers.batch.kyn.AgentactionPK</class>
		<class>com.farmers.batch.kyn.Smartrule</class>
		<class>com.farmers.batch.kyn.Agentdetail</class>
		<class>com.farmers.batch.kyn.Reportview</class>
		<class>com.farmers.batch.kyn.ReportviewPK</class>
		<shared-cache-mode>ENABLE_SELECTIVE</shared-cache-mode>
	</persistence-unit>
</persistence>
